g2fl/__init__.py
g2fl/common.py
g2fl/dl.py
g2fl/dldata.py
g2fl/plotting.py
g2fl/rnn.py
g2fl/train.py
g2fl-0.0.45.dist-info/METADATA
g2fl-0.0.45.dist-info/WHEEL
g2fl-0.0.45.dist-info/licenses/LICENSE
g2fl-0.0.45.dist-info/RECORD
