Metadata-Version: 2.1
Name: g2fl
Version: 0.0.45
Summary: gavin's function library
Author-email: chenlh <gavinlhchen@gmail.com>
License-File: LICENSE
Classifier: License :: OSI Approved :: MIT License
Classifier: Operating System :: OS Independent
Classifier: Programming Language :: Python :: 3
Requires-Python: >=3.10
Requires-Dist: matplotlib-inline==0.1.6
Requires-Dist: matplotlib==3.7.4
Requires-Dist: pytest==8.0.0
Requires-Dist: torch==2.2.0
Requires-Dist: torchvision==0.17.0
